docs/__init__.py
docs/agents.md
docs/design/agent_eval.md
docs/design/agent_optimizer.md
docs/design/event_based_waiting.md
docs/design/human_step.md
docs/design/io_api.md
docs/design/io_presentation_contract.md
docs/design/migrations.md
docs/design/nested_steps.md
docs/design/planar_file.md
docs/design/step_id.md
docs/entities.md
docs/evals.md
docs/files.md
docs/generate_llm_prompt.py
docs/human_tasks.md
docs/io.md
docs/llm_prompt.md
docs/llm_prompt.template.md
docs/package-releases.md
docs/planar_dataset.md
docs/scheduling.md
docs/sqlalchemy_usage.md
docs/test_docs.py
docs/testing_workflows.md
docs/workflows.md
planar/__init__.py
planar/ai/__init__.py
planar/ai/agent.py
planar/ai/agent_base.py
planar/ai/agent_utils.py
planar/ai/factories.py
planar/ai/io_agent.py
planar/ai/model_registry.py
planar/ai/models.py
planar/ai/pydantic_ai.py
planar/ai/tool_context.py
planar/ai/utils.py
planar/app.py
planar/cli.py
planar/cli_agent.py
planar/cli_agent_tui.py
planar/config.py
planar/cron_expression_normalizer.py
planar/data/__init__.py
planar/data/config.py
planar/data/connection.py
planar/data/dataset.py
planar/data/exceptions.py
planar/data/utils.py
planar/db/__init__.py
planar/db/alembic/env.py
planar/db/alembic/script.py.mako
planar/db/alembic/versions/037a443d64b2_add_user_and_group_tables.py
planar/db/alembic/versions/04401bc785c8_add_changelog.py
planar/db/alembic/versions/3476068c153c_initial_system_tables_migration.py
planar/db/alembic/versions/3b1822ff9d93_add_workflow_step_meta_payload.py
planar/db/alembic/versions/3cde71bdea7a_add_scheduling_fields.py
planar/db/alembic/versions/4ca7ba90cdbc_add_idpgroup_num_active_members.py
planar/db/alembic/versions/7891b1eb00e4_add_error_fields_to_eval_tables.py
planar/db/alembic/versions/7bd0247a8112_add_eval_tables.py
planar/db/alembic/versions/8855a78a408f_message_step_type.py
planar/db/alembic/versions/9e3c9daaf42a_add_workflow_cancelled_at_field.py
planar-0.23.1.dist-info/WHEEL
planar-0.23.1.dist-info/entry_points.txt
planar-0.23.1.dist-info/METADATA
planar-0.23.1.dist-info/RECORD
