Metadata-Version: 2.4
Name: planar
Version: 0.23.1
Summary: Batteries-included framework for building durable agentic workflows and business applications.
License-Expression: LicenseRef-Proprietary
Requires-Dist: aiofiles>=24.1.0
Requires-Dist: aiosqlite>=0.21.0,<0.22.0
Requires-Dist: alembic>=1.14.1
Requires-Dist: claude-agent-sdk>=0.1.2
Requires-Dist: asyncpg
Requires-Dist: boto3>=1.39.15
Requires-Dist: cedarpy>=4.1.0
Requires-Dist: fastapi[standard-no-fastapi-cloud-cli]>=0.119.0
Requires-Dist: inflection>=0.5.1
Requires-Dist: pydantic-ai-slim[anthropic,bedrock,google,openai]>=1.10.0
Requires-Dist: pygments>=2.19.1
Requires-Dist: rich>=13.9.4
Requires-Dist: pyjwt[crypto]
Requires-Dist: python-multipart>=0.0.20
Requires-Dist: sqlalchemy[asyncio]>=2.0.37
Requires-Dist: sqlmodel>=0.0.22
Requires-Dist: typer>=0.15.2
Requires-Dist: typing-extensions>=4.12.2
Requires-Dist: zen-engine>=0.40.0
Requires-Dist: prompt-toolkit>=3.0.52
Requires-Dist: croniter>=6.0.0
Requires-Dist: uuid-utils>=0.9.0
Requires-Dist: adlfs>=2025.8.0 ; extra == 'azure'
Requires-Dist: azure-storage-blob>=12.19.0 ; extra == 'azure'
Requires-Dist: azure-identity>=1.15.0 ; extra == 'azure'
Requires-Dist: aiohttp>=3.8.0 ; extra == 'azure'
Requires-Dist: duckdb>=1.4.1 ; extra == 'data'
Requires-Dist: ibis-framework[duckdb]>=11.0.0 ; extra == 'data'
Requires-Dist: polars>=1.31.0 ; extra == 'data'
Requires-Dist: opentelemetry-api>=1.34.1 ; extra == 'otel'
Requires-Dist: opentelemetry-exporter-otlp>=1.34.1 ; extra == 'otel'
Requires-Dist: opentelemetry-instrumentation-logging>=0.55b1 ; extra == 'otel'
Requires-Dist: opentelemetry-sdk>=1.34.1 ; extra == 'otel'
Requires-Python: >=3.12
Provides-Extra: azure
Provides-Extra: data
Provides-Extra: otel
